ranchero/__init__.py
ranchero/analyze.py
ranchero/config.py
ranchero/config.yaml
ranchero/extract.py
ranchero/merge.py
ranchero/neigh.py
ranchero/query.py
ranchero/read_file.py
ranchero/standardize.py
ranchero/summarize.py
ranchero/statics/HPRC_sample_ids.py
ranchero/statics/countries.py
ranchero/statics/drop_zone.py
ranchero/statics/file_extensions.py
ranchero/statics/host_disease.py
ranchero/statics/host_species.py
ranchero/statics/kolumns.py
ranchero/statics/null_values.py
ranchero/statics/regions.py
ranchero/statics/sample_sources.py
ranchero/statics/taxoncore_v4.tsv
ranchero/statics/tuberculosis_taxonomy.py
ranchero/statics/unused/center_names.py
ranchero/statics/unused/tuberculosis_other_names.py
ranchero-0.1.0rc31.dist-info/licenses/LICENSE
ranchero-0.1.0rc31.dist-info/METADATA
ranchero-0.1.0rc31.dist-info/WHEEL
ranchero-0.1.0rc31.dist-info/top_level.txt
ranchero-0.1.0rc31.dist-info/RECORD
