Metadata-Version: 2.4
Name: ranchero
Version: 0.1.0rc31
Summary: Ranchero: metadata wrangling for bioinformatics
Author: Ash O'Farrell
License-Expression: GPL-3.0
Requires-Python: >=3.10
License-File: LICENSE
Requires-Dist: pandas>=2.0.0
Requires-Dist: polars==1.27.0
Requires-Dist: pyarrow
Requires-Dist: tqdm
Requires-Dist: xmltodict==0.14.2
Requires-Dist: pyyaml
Dynamic: license-file
